[
  { "title": "A Cappella" },
  { "title": "Abstract" },
  { "title": "Abstract Beats" },
  { "title": "Abstract Hip Hop" },
  { "title": "Abstract Idm" },
  { "title": "Abstractro" },
  { "title": "Accordion" },
  { "title": "Acid House" },
  { "title": "Acid Jazz" },
  { "title": "Acid Techno" },
  { "title": "Acousmatic" },
  { "title": "Acoustic Blues" },
  { "title": "Acoustic Pop" },
  { "title": "Adult Standards" },
  { "title": "African Percussion" },
  { "title": "African Rock" },
  { "title": "Afrikaans" },
  { "title": "Afrobeat" },
  { "title": "Afrobeats" },
  { "title": "Aggrotech" },
  { "title": "Albanian Pop" },
  { "title": "Album Rock" },
  { "title": "Albuquerque Indie" },
  { "title": "Alternative Americana" },
  { "title": "Alternative Country" },
  { "title": "Alternative Dance" },
  { "title": "Alternative Emo" },
  { "title": "Alternative Hardcore" },
  { "title": "Alternative Hip Hop" },
  { "title": "Alternative Metal" },
  { "title": "Alternative Metalcore" },
  { "title": "Alternative New Age" },
  { "title": "Alternative Pop" },
  { "title": "Alternative Pop Rock" },
  { "title": "Alternative R&b" },
  { "title": "Alternative Rock" },
  { "title": "Alternative Roots Rock" },
  { "title": "Ambeat" },
  { "title": "Ambient" },
  { "title": "Ambient Dub Techno" },
  { "title": "Ambient Fusion" },
  { "title": "Ambient Idm" },
  { "title": "Ambient Psychill" },
  { "title": "Ambient Trance" },
  { "title": "Anarcho-punk" },
  { "title": "Andean" },
  { "title": "Anime" },
  { "title": "Anime Score" },
  { "title": "Anti-folk" },
  { "title": "Antiviral Pop" },
  { "title": "Appalachian Folk" },
  { "title": "Arab Folk" },
  { "title": "Arab Pop" },
  { "title": "Arabesk" },
  { "title": "Argentine Indie" },
  { "title": "Argentine Reggae" },
  { "title": "Argentine Rock" },
  { "title": "Armenian Folk" },
  { "title": "Art Rock" },
  { "title": "Athens Indie" },
  { "title": "Atmospheric Black Metal" },
  { "title": "Atmospheric Post Rock" },
  { "title": "Atmospheric Post-metal" },
  { "title": "Aussietronica" },
  { "title": "Austindie" },
  { "title": "Australian Alternative Rock" },
  { "title": "Australian Country" },
  { "title": "Australian Dance" },
  { "title": "Australian Hip Hop" },
  { "title": "Australian Indie" },
  { "title": "Australian Pop" },
  { "title": "Austrian Hip Hop" },
  { "title": "Austropop" },
  { "title": "Avant-garde" },
  { "title": "Avant-garde Jazz" },
  { "title": "Avantgarde Metal" },
  { "title": "Axe" },
  { "title": "Azonto" },
  { "title": "Bachata" },
  { "title": "Baile Funk" },
  { "title": "Balearic" },
  { "title": "Balkan Brass" },
  { "title": "Banda" },
  { "title": "Bangla" },
  { "title": "Barbershop" },
  { "title": "Barnemusikk" },
  { "title": "Barnmusik" },
  { "title": "Baroque" },
  { "title": "Baroque Ensemble" },
  { "title": "Basque Rock" },
  { "title": "Bass Music" },
  { "title": "Bass Trip" },
  { "title": "Bassline" },
  { "title": "Bay Area Hip Hop" },
  { "title": "Beach Music" },
  { "title": "Beatdown" },
  { "title": "Beats & Rhymes" },
  { "title": "Bebop" },
  { "title": "Belgian Indie" },
  { "title": "Belgian Rock" },
  { "title": "Belly Dance" },
  { "title": "Belorush" },
  { "title": "Bemani" },
  { "title": "Benga" },
  { "title": "Bhangra" },
  { "title": "Big Band" },
  { "title": "Big Beat" },
  { "title": "Big Room" },
  { "title": "Black Death" },
  { "title": "Black Metal" },
  { "title": "Black Sludge" },
  { "title": "Black Thrash" },
  { "title": "Blackgaze" },
  { "title": "Blaskapelle" },
  { "title": "Bluegrass" },
  { "title": "Blues" },
  { "title": "Blues-rock" },
  { "title": "Blues-rock Guitar" },
  { "title": "Bmore" },
  { "title": "Bolero" },
  { "title": "Boogaloo" },
  { "title": "Boogie-woogie" },
  { "title": "Bossa Nova" },
  { "title": "Bossa Nova Jazz" },
  { "title": "Boston Rock" },
  { "title": "Bounce" },
  { "title": "Bouncy House" },
  { "title": "Bow Pop" },
  { "title": "Boy Band" },
  { "title": "Brass Band" },
  { "title": "Brass Ensemble" },
  { "title": "Brazilian Composition" },
  { "title": "Brazilian Gospel" },
  { "title": "Brazilian Hip Hop" },
  { "title": "Brazilian Indie" },
  { "title": "Brazilian Pop Music" },
  { "title": "Brazilian Punk" },
  { "title": "Breakbeat" },
  { "title": "Breakcore" },
  { "title": "Breaks" },
  { "title": "Brega" },
  { "title": "Breton Folk" },
  { "title": "Brill Building Pop" },
  { "title": "British Alternative Rock" },
  { "title": "British Blues" },
  { "title": "British Brass Band" },
  { "title": "British Dance Band" },
  { "title": "British Folk" },
  { "title": "British Indie Rock" },
  { "title": "British Invasion" },
  { "title": "Britpop" },
  { "title": "Broadway" },
  { "title": "Broken Beat" },
  { "title": "Brooklyn Indie" },
  { "title": "Brostep" },
  { "title": "Brutal Death Metal" },
  { "title": "Brutal Deathcore" },
  { "title": "Bubble Trance" },
  { "title": "Bubblegum Dance" },
  { "title": "Bubblegum Pop" },
  { "title": "Bulgarian Rock" },
  { "title": "Byzantine" },
  { "title": "C-pop" },
  { "title": "C64" },
  { "title": "C86" },
  { "title": "Cabaret" },
  { "title": "Cajun" },
  { "title": "Calypso" },
  { "title": "Canadian Country" },
  { "title": "Canadian Hip Hop" },
  { "title": "Canadian Indie" },
  { "title": "Canadian Metal" },
  { "title": "Canadian Pop" },
  { "title": "Candy Pop" },
  { "title": "Cantautor" },
  { "title": "Cante Flamenco" },
  { "title": "Canterbury Scene" },
  { "title": "Cantopop" },
  { "title": "Canzone Napoletana" },
  { "title": "Capoeira" },
  { "title": "Carnatic" },
  { "title": "Catstep" },
  { "title": "Caucasian Folk" },
  { "title": "Ccm" },
  { "title": "Ceilidh" },
  { "title": "Cello" },
  { "title": "Celtic" },
  { "title": "Celtic Christmas" },
  { "title": "Celtic Punk" },
  { "title": "Celtic Rock" },
  { "title": "Central Asian Folk" },
  { "title": "Chalga" },
  { "title": "Chamber Pop" },
  { "title": "Chanson" },
  { "title": "Chanson Quebecois" },
  { "title": "Chaotic Black Metal" },
  { "title": "Chaotic Hardcore" },
  { "title": "Charred Death" },
  { "title": "Chicago Blues" },
  { "title": "Chicago House" },
  { "title": "Chicago Indie" },
  { "title": "Chicago Soul" },
  { "title": "Chicano Rap" },
  { "title": "Children's Christmas" },
  { "title": "Children's Music" },
  { "title": "Chilean Rock" },
  { "title": "Chill Groove" },
  { "title": "Chill Lounge" },
  { "title": "Chill-out" },
  { "title": "Chill-out Trance" },
  { "title": "Chillstep" },
  { "title": "Chillwave" },
  { "title": "Chinese Indie Rock" },
  { "title": "Chinese Opera" },
  { "title": "Chinese Traditional" },
  { "title": "Chip Hop" },
  { "title": "Chiptune" },
  { "title": "Choral" },
  { "title": "Choro" },
  { "title": "Christian Alternative Rock" },
  { "title": "Christian Christmas" },
  { "title": "Christian Dance" },
  { "title": "Christian Hardcore" },
  { "title": "Christian Hip Hop" },
  { "title": "Christian Metal" },
  { "title": "Christian Music" },
  { "title": "Christian Punk" },
  { "title": "Christian Rock" },
  { "title": "Christmas" },
  { "title": "Christmas Product" },
  { "title": "Cinematic Dubstep" },
  { "title": "Clarinet" },
  { "title": "Classic Afrobeat" },
  { "title": "Classic Belgian Pop" },
  { "title": "Classic Chinese Pop" },
  { "title": "Classic Colombian Pop" },
  { "title": "Classic Czech Pop" },
  { "title": "Classic Danish Pop" },
  { "title": "Classic Dutch Pop" },
  { "title": "Classic Eurovision" },
  { "title": "Classic Finnish Pop" },
  { "title": "Classic Finnish Rock" },
  { "title": "Classic French Pop" },
  { "title": "Classic Funk Rock" },
  { "title": "Classic Garage Rock" },
  { "title": "Classic Italian Pop" },
  { "title": "Classic Norwegian Pop" },
  { "title": "Classic Peruvian Pop" },
  { "title": "Classic Polish Pop" },
  { "title": "Classic Psychedelic Rock" },
  { "title": "Classic Rock" },
  { "title": "Classic Russian Pop" },
  { "title": "Classic Russian Rock" },
  { "title": "Classic Schlager" },
  { "title": "Classic Soundtrack" },
  { "title": "Classic Swedish Pop" },
  { "title": "Classic Turkish Pop" },
  { "title": "Classic Venezuelan Pop" },
  { "title": "Classical" },
  { "title": "Classical Christmas" },
  { "title": "Classical Flute" },
  { "title": "Classical Guitar" },
  { "title": "Classical Organ" },
  { "title": "Classical Performance" },
  { "title": "Classical Period" },
  { "title": "Classical Piano" },
  { "title": "College A Cappella" },
  { "title": "College Marching Band" },
  { "title": "Colombian Rock" },
  { "title": "Columbus Ohio Indie" },
  { "title": "Comedy" },
  { "title": "Comedy Rock" },
  { "title": "Comic" },
  { "title": "Commons" },
  { "title": "Complextro" },
  { "title": "Composition D" },
  { "title": "Concert Piano" },
  { "title": "Consort" },
  { "title": "Contemporary Classical" },
  { "title": "Contemporary Country" },
  { "title": "Contemporary Folk" },
  { "title": "Contemporary Jazz" },
  { "title": "Contemporary Post-bop" },
  { "title": "Cool Jazz" },
  { "title": "Corrosion" },
  { "title": "Corsican Folk" },
  { "title": "Country" },
  { "title": "Country Blues" },
  { "title": "Country Christmas" },
  { "title": "Country Dawn" },
  { "title": "Country Gospel" },
  { "title": "Country Road" },
  { "title": "Country Rock" },
  { "title": "Coupe Decale" },
  { "title": "Coverchill" },
  { "title": "Covertrance" },
  { "title": "Cowboy Western" },
  { "title": "Cowpunk" },
  { "title": "Crack Rock Steady" },
  { "title": "Croatian Pop" },
  { "title": "Crossover Prog" },
  { "title": "Crossover Thrash" },
  { "title": "Crunk" },
  { "title": "Crust Punk" },
  { "title": "Cryptic Black Metal" },
  { "title": "Cuban Rumba" },
  { "title": "Cubaton" },
  { "title": "Cumbia" },
  { "title": "Cumbia Funk" },
  { "title": "Cumbia Sonidera" },
  { "title": "Cumbia Villera" },
  { "title": "Cyber Metal" },
  { "title": "Czech Folk" },
  { "title": "Czech Rock" },
  { "title": "Dallas Indie" },
  { "title": "Dance Pop" },
  { "title": "Dance Rock" },
  { "title": "Dance-punk" },
  { "title": "Dancehall" },
  { "title": "Dangdut" },
  { "title": "Danish Hip Hop" },
  { "title": "Danish Indie" },
  { "title": "Danish Jazz" },
  { "title": "Danish Pop" },
  { "title": "Danish Pop Rock" },
  { "title": "Dansband" },
  { "title": "Danseband" },
  { "title": "Dansktop" },
  { "title": "Dark Ambient" },
  { "title": "Dark Black Metal" },
  { "title": "Dark Cabaret" },
  { "title": "Dark Electro-industrial" },
  { "title": "Dark Hardcore" },
  { "title": "Dark Jazz" },
  { "title": "Dark Minimal Techno" },
  { "title": "Dark Progressive House" },
  { "title": "Dark Psytrance" },
  { "title": "Dark Wave" },
  { "title": "Darkstep" },
  { "title": "Death Core" },
  { "title": "Death Metal" },
  { "title": "Deathgrind" },
  { "title": "Deep Acoustic Pop" },
  { "title": "Deep Adult Standards" },
  { "title": "Deep Alternative R&b" },
  { "title": "Deep Ambient" },
  { "title": "Deep Baroque" },
  { "title": "Deep Brazilian Pop" },
  { "title": "Deep Breakcore" },
  { "title": "Deep Canadian Indie" },
  { "title": "Deep Ccm" },
  { "title": "Deep Cello" },
  { "title": "Deep Chill" },
  { "title": "Deep Chill-out" },
  { "title": "Deep Christian Rock" },
  { "title": "Deep Classic Garage Rock" },
  { "title": "Deep Classical Piano" },
  { "title": "Deep Comedy" },
  { "title": "Deep Contemporary Country" },
  { "title": "Deep Dance Pop" },
  { "title": "Deep Darkpsy" },
  { "title": "Deep Deep House" },
  { "title": "Deep Deep Tech House" },
  { "title": "Deep Delta Blues" },
  { "title": "Deep Disco" },
  { "title": "Deep Disco House" },
  { "title": "Deep Discofox" },
  { "title": "Deep Downtempo Fusion" },
  { "title": "Deep Dub Techno" },
  { "title": "Deep East Coast Hip Hop" },
  { "title": "Deep Euro House" },
  { "title": "Deep Eurodance" },
  { "title": "Deep Filthstep" },
  { "title": "Deep Flow" },
  { "title": "Deep Folk Metal" },
  { "title": "Deep Free Jazz" },
  { "title": "Deep Freestyle" },
  { "title": "Deep Full On" },
  { "title": "Deep Funk" },
  { "title": "Deep Funk House" },
  { "title": "Deep G Funk" },
  { "title": "Deep German Indie" },
  { "title": "Deep German Punk" },
  { "title": "Deep Gothic Post-punk" },
  { "title": "Deep Happy Hardcore" },
  { "title": "Deep Hardcore" },
  { "title": "Deep Hardcore Punk" },
  { "title": "Deep Hardstyle" },
  { "title": "Deep House" },
  { "title": "Deep Indian Pop" },
  { "title": "Deep Indie Pop" },
  { "title": "Deep Indie Rock" },
  { "title": "Deep Indie Singer-songwriter" },
  { "title": "Deep Italo Disco" },
  { "title": "Deep Jazz Fusion" },
  { "title": "Deep Jazz Guitar" },
  { "title": "Deep Jazz Piano" },
  { "title": "Deep Latin Alternative" },
  { "title": "Deep Liquid" },
  { "title": "Deep Liquid Bass" },
  { "title": "Deep Melodic Death Metal" },
  { "title": "Deep Melodic Hard Rock" },
  { "title": "Deep Melodic House" },
  { "title": "Deep Melodic Metalcore" },
  { "title": "Deep Minimal Techno" },
  { "title": "Deep Motown" },
  { "title": "Deep Neo-synthpop" },
  { "title": "Deep Neofolk" },
  { "title": "Deep New Wave" },
  { "title": "Deep Nordic Folk" },
  { "title": "Deep Northern Soul" },
  { "title": "Deep Opera" },
  { "title": "Deep Orchestral" },
  { "title": "Deep Orgcore" },
  { "title": "Deep Pop Emo" },
  { "title": "Deep Pop Punk" },
  { "title": "Deep Power-pop Punk" },
  { "title": "Deep Progressive House" },
  { "title": "Deep Progressive Trance" },
  { "title": "Deep Psychobilly" },
  { "title": "Deep Psytrance" },
  { "title": "Deep Punk Rock" },
  { "title": "Deep Ragga" },
  { "title": "Deep Rai" },
  { "title": "Deep Regional Mexican" },
  { "title": "Deep Smooth Jazz" },
  { "title": "Deep Soft Rock" },
  { "title": "Deep Soul House" },
  { "title": "Deep Soundtrack" },
  { "title": "Deep Southern Soul" },
  { "title": "Deep Space Rock" },
  { "title": "Deep String Quartet" },
  { "title": "Deep Sunset Lounge" },
  { "title": "Deep Surf Music" },
  { "title": "Deep Symphonic Black Metal" },
  { "title": "Deep Talent Show" },
  { "title": "Deep Tech House" },
  { "title": "Deep Thrash Metal" },
  { "title": "Deep Trap" },
  { "title": "Deep Turkish Pop" },
  { "title": "Deep Uplifting Trance" },
  { "title": "Deep Vocal House" },
  { "title": "Deep Vocal Jazz" },
  { "title": "Delta Blues" },
  { "title": "Demoscene" },
  { "title": "Denver Indie" },
  { "title": "Depressive Black Metal" },
  { "title": "Desert Blues" },
  { "title": "Desi" },
  { "title": "Destroy Techno" },
  { "title": "Detroit Hip Hop" },
  { "title": "Detroit Techno" },
  { "title": "Didgeridoo" },
  { "title": "Digital Hardcore" },
  { "title": "Dirty South Rap" },
  { "title": "Dirty Texas Rap" },
  { "title": "Disco" },
  { "title": "Disco House" },
  { "title": "Discofox" },
  { "title": "Dixieland" },
  { "title": "Djent" },
  { "title": "Dominican Pop" },
  { "title": "Doo-wop" },
  { "title": "Doom Metal" },
  { "title": "Doomcore" },
  { "title": "Doujin" },
  { "title": "Downtempo" },
  { "title": "Downtempo Fusion" },
  { "title": "Downtempo Trip Hop" },
  { "title": "Drama" },
  { "title": "Dream Pop" },
  { "title": "Dreamo" },
  { "title": "Drill And Bass" },
  { "title": "Drone" },
  { "title": "Drone Folk" },
  { "title": "Drone Metal" },
  { "title": "Drone Psych" },
  { "title": "Drum And Bass" },
  { "title": "Drumfunk" },
  { "title": "Dub" },
  { "title": "Dub Techno" },
  { "title": "Dubstep" },
  { "title": "Dubstep Product" },
  { "title": "Dubsteppe" },
  { "title": "Duranguense" },
  { "title": "Dutch Hip Hop" },
  { "title": "Dutch House" },
  { "title": "Dutch Pop" },
  { "title": "Dutch Rock" },
  { "title": "E6fi" },
  { "title": "Early Music" },
  { "title": "Early Music Ensemble" },
  { "title": "East Coast Hip Hop" },
  { "title": "Easy Listening" },
  { "title": "Ebm" },
  { "title": "Ectofolk" },
  { "title": "Ecuadoria" },
  { "title": "Edm" },
  { "title": "Electric Blues" },
  { "title": "Electro" },
  { "title": "Electro Dub" },
  { "title": "Electro House" },
  { "title": "Electro Jazz" },
  { "title": "Electro Latino" },
  { "title": "Electro Swing" },
  { "title": "Electro Trash" },
  { "title": "Electro-industrial" },
  { "title": "Electroacoustic Improvisation" },
  { "title": "Electroclash" },
  { "title": "Electrofox" },
  { "title": "Electronic" },
  { "title": "Electronica" },
  { "title": "Electronicore" },
  { "title": "Electropowerpop" },
  { "title": "Electropunk" },
  { "title": "Emo" },
  { "title": "Emo Punk" },
  { "title": "Enka" },
  { "title": "Entehno" },
  { "title": "Environmental" },
  { "title": "Epicore" },
  { "title": "Estonian Pop" },
  { "title": "Ethereal Gothic" },
  { "title": "Ethereal Wave" },
  { "title": "Etherpop" },
  { "title": "Ethiopian Pop" },
  { "title": "Eurobeat" },
  { "title": "Eurodance" },
  { "title": "Europop" },
  { "title": "Euroska" },
  { "title": "Eurovision" },
  { "title": "Exotica" },
  { "title": "Experimental" },
  { "title": "Experimental Dubstep" },
  { "title": "Experimental Psych" },
  { "title": "Experimental Rock" },
  { "title": "Fado" },
  { "title": "Fake" },
  { "title": "Fallen Angel" },
  { "title": "Faroese Pop" },
  { "title": "Fast Melodic Punk" },
  { "title": "Fidget House" },
  { "title": "Filmi" },
  { "title": "Filter House" },
  { "title": "Filthstep" },
  { "title": "Fingerstyle" },
  { "title": "Finnish Hardcore" },
  { "title": "Finnish Hip Hop" },
  { "title": "Finnish Indie" },
  { "title": "Finnish Jazz" },
  { "title": "Finnish Metal" },
  { "title": "Finnish Pop" },
  { "title": "Flamenco" },
  { "title": "Flick Hop" },
  { "title": "Folk" },
  { "title": "Folk Christmas" },
  { "title": "Folk Metal" },
  { "title": "Folk Punk" },
  { "title": "Folk Rock" },
  { "title": "Folk-pop" },
  { "title": "Folk-prog" },
  { "title": "Folklore Argentino" },
  { "title": "Folkmusik" },
  { "title": "Footwork" },
  { "title": "Forro" },
  { "title": "Fourth World" },
  { "title": "Freak Folk" },
  { "title": "Freakbeat" },
  { "title": "Free Improvisation" },
  { "title": "Free Jazz" },
  { "title": "Freestyle" },
  { "title": "French Folk" },
  { "title": "French Folk Pop" },
  { "title": "French Hip Hop" },
  { "title": "French Indie Pop" },
  { "title": "French Movie Tunes" },
  { "title": "French Pop" },
  { "title": "French Punk" },
  { "title": "French Reggae" },
  { "title": "French Rock" },
  { "title": "Full On" },
  { "title": "Funeral Doom" },
  { "title": "Funk" },
  { "title": "Funk Carioca" },
  { "title": "Funk Metal" },
  { "title": "Funk Rock" },
  { "title": "Funky Breaks" },
  { "title": "Future Ambient" },
  { "title": "Future Garage" },
  { "title": "Futurepop" },
  { "title": "G Funk" },
  { "title": "Gabba" },
  { "title": "Galego" },
  { "title": "Gamecore" },
  { "title": "Gamelan" },
  { "title": "Gangster Rap" },
  { "title": "Garage Pop" },
  { "title": "Garage Punk" },
  { "title": "Garage Punk Blues" },
  { "title": "Garage Rock" },
  { "title": "Gauze Pop" },
  { "title": "Gbvfi" },
  { "title": "Geek Folk" },
  { "title": "Geek Rock" },
  { "title": "German Ccm" },
  { "title": "German Hip Hop" },
  { "title": "German Indie" },
  { "title": "German Metal" },
  { "title": "German Oi" },
  { "title": "German Pop" },
  { "title": "German Pop Rock" },
  { "title": "German Punk" },
  { "title": "German Show Tunes" },
  { "title": "German Techno" },
  { "title": "Ghettotech" },
  { "title": "Ghoststep" },
  { "title": "Girl Group" },
  { "title": "Glam Metal" },
  { "title": "Glam Rock" },
  { "title": "Glitch" },
  { "title": "Glitch Beats" },
  { "title": "Glitch Hop" },
  { "title": "Glitter Trance" },
  { "title": "Goa Trance" },
  { "title": "Goregrind" },
  { "title": "Gospel" },
  { "title": "Gospel Blues" },
  { "title": "Gospel Reggae" },
  { "title": "Gothic Alternative" },
  { "title": "Gothic Americana" },
  { "title": "Gothic Doom" },
  { "title": "Gothic Metal" },
  { "title": "Gothic Post-punk" },
  { "title": "Gothic Rock" },
  { "title": "Gothic Symphonic Metal" },
  { "title": "Grave Wave" },
  { "title": "Greek Hip Hop" },
  { "title": "Greek House" },
  { "title": "Greek Indie" },
  { "title": "Grim Death Metal" },
  { "title": "Grime" },
  { "title": "Grindcore" },
  { "title": "Grisly Death Metal" },
  { "title": "Groove Metal" },
  { "title": "Grunge" },
  { "title": "Grunge Pop" },
  { "title": "Grupera" },
  { "title": "Guidance" },
  { "title": "Gypsy Jazz" },
  { "title": "Hands Up" },
  { "title": "Happy Hardcore" },
  { "title": "Hard Alternative" },
  { "title": "Hard Bop" },
  { "title": "Hard Glam" },
  { "title": "Hard House" },
  { "title": "Hard Rock" },
  { "title": "Hard Stoner Rock" },
  { "title": "Hard Trance" },
  { "title": "Hardcore" },
  { "title": "Hardcore Breaks" },
  { "title": "Hardcore Hip Hop" },
  { "title": "Hardcore Punk" },
  { "title": "Hardcore Techno" },
  { "title": "Hardstyle" },
  { "title": "Harmonica Blues" },
  { "title": "Harp" },
  { "title": "Hatecore" },
  { "title": "Hauntology" },
  { "title": "Hawaiian" },
  { "title": "Healing" },
  { "title": "Heavy Alternative" },
  { "title": "Heavy Christmas" },
  { "title": "Heavy Gothic Rock" },
  { "title": "Hi Nrg" },
  { "title": "Highlife" },
  { "title": "Hindustani Classical" },
  { "title": "Hip Hop" },
  { "title": "Hip Hop Quebecois" },
  { "title": "Hip Hop Tuga" },
  { "title": "Hip House" },
  { "title": "Hip Pop" },
  { "title": "Hiplife" },
  { "title": "Hoerspiel" },
  { "title": "Hollywood" },
  { "title": "Honky Tonk" },
  { "title": "Horror Punk" },
  { "title": "Horrorcore" },
  { "title": "House" },
  { "title": "Hungarian Hip Hop" },
  { "title": "Hungarian Pop" },
  { "title": "Hungarian Rock" },
  { "title": "Hurban" },
  { "title": "Hyphy" },
  { "title": "Icelandic Pop" },
  { "title": "Idol" },
  { "title": "Illbient" },
  { "title": "Indian Classical" },
  { "title": "Indian Pop" },
  { "title": "Indian Rock" },
  { "title": "Indie Christmas" },
  { "title": "Indie Dream Pop" },
  { "title": "Indie Emo" },
  { "title": "Indie Emo Rock" },
  { "title": "Indie Folk" },
  { "title": "Indie Fuzzpop" },
  { "title": "Indie Pop" },
  { "title": "Indie Pop Rock" },
  { "title": "Indie Post-punk" },
  { "title": "Indie Psych-pop" },
  { "title": "Indie R&b" },
  { "title": "Indie Rock" },
  { "title": "Indie Shoegaze" },
  { "title": "Indie Singer-songwriter" },
  { "title": "Indietronica" },
  { "title": "Indonesian Indie" },
  { "title": "Indonesian Pop" },
  { "title": "Indorock" },
  { "title": "Industrial" },
  { "title": "Industrial Metal" },
  { "title": "Industrial Rock" },
  { "title": "Instrumental Post Rock" },
  { "title": "Intelligent Dance Music" },
  { "title": "Irish Folk" },
  { "title": "Irish Indie" },
  { "title": "Irish Rock" },
  { "title": "Iskelma" },
  { "title": "Islamic Recitation" },
  { "title": "Israeli Rock" },
  { "title": "Italian Disco" },
  { "title": "Italian Folk" },
  { "title": "Italian Hip Hop" },
  { "title": "Italian Indie Pop" },
  { "title": "Italian Jazz" },
  { "title": "Italian Pop" },
  { "title": "Italian Pop Rock" },
  { "title": "Italian Progressive Rock" },
  { "title": "Italian Punk" },
  { "title": "Italo Dance" },
  { "title": "J-alt" },
  { "title": "J-ambient" },
  { "title": "J-core" },
  { "title": "J-dance" },
  { "title": "J-idol" },
  { "title": "J-indie" },
  { "title": "J-metal" },
  { "title": "J-pop" },
  { "title": "J-poppunk" },
  { "title": "J-poprock" },
  { "title": "J-punk" },
  { "title": "J-rap" },
  { "title": "J-rock" },
  { "title": "J-theme" },
  { "title": "Jam Band" },
  { "title": "Jangle Pop" },
  { "title": "Jangle Rock" },
  { "title": "Japanese Jazztronica" },
  { "title": "Japanese Psychedelic" },
  { "title": "Japanese R&b" },
  { "title": "Japanese Standards" },
  { "title": "Japanese Traditional" },
  { "title": "Japanoise" },
  { "title": "Jazz" },
  { "title": "Jazz Bass" },
  { "title": "Jazz Blues" },
  { "title": "Jazz Brass" },
  { "title": "Jazz Christmas" },
  { "title": "Jazz Funk" },
  { "title": "Jazz Fusion" },
  { "title": "Jazz Metal" },
  { "title": "Jazz Orchestra" },
  { "title": "Jazz Trio" },
  { "title": "Jerk" },
  { "title": "Jig And Reel" },
  { "title": "Judaica" },
  { "title": "Jug Band" },
  { "title": "Juggalo" },
  { "title": "Jump Blues" },
  { "title": "Jump Up" },
  { "title": "Jumpstyle" },
  { "title": "Jungle" },
  { "title": "K-hop" },
  { "title": "K-indie" },
  { "title": "K-pop" },
  { "title": "K-rock" },
  { "title": "Kabarett" },
  { "title": "Karneval" },
  { "title": "Kc Indie" },
  { "title": "Kindermusik" },
  { "title": "Kirtan" },
  { "title": "Kiwi Rock" },
  { "title": "Kizomba" },
  { "title": "Klapa" },
  { "title": "Klezmer" },
  { "title": "Kompa" },
  { "title": "Kraut Rock" },
  { "title": "Kuduro" },
  { "title": "Kurdish Folk" },
  { "title": "Kwaito" },
  { "title": "La Indie" },
  { "title": "Laboratorio" },
  { "title": "Laiko" },
  { "title": "Latin" },
  { "title": "Latin Alternative" },
  { "title": "Latin Christian" },
  { "title": "Latin Christmas" },
  { "title": "Latin Electronica" },
  { "title": "Latin Hip Hop" },
  { "title": "Latin Jazz" },
  { "title": "Latin Metal" },
  { "title": "Latin Pop" },
  { "title": "Latvian Pop" },
  { "title": "Lds" },
  { "title": "Leeds Indie" },
  { "title": "Levenslied" },
  { "title": "Liedermacher" },
  { "title": "Light Music" },
  { "title": "Lilith" },
  { "title": "Liquid Funk" },
  { "title": "Lithumania" },
  { "title": "Liturgical" },
  { "title": "Lo Star" },
  { "title": "Lo-fi" },
  { "title": "Louisiana Blues" },
  { "title": "Louisville Indie" },
  { "title": "Lounge" },
  { "title": "Lounge House" },
  { "title": "Lovers Rock" },
  { "title": "Lowercase" },
  { "title": "Luk Thung" },
  { "title": "Madchester" },
  { "title": "Maghreb" },
  { "title": "Magyar" },
  { "title": "Makossa" },
  { "title": "Malagasy Folk" },
  { "title": "Malaysian Pop" },
  { "title": "Mallet" },
  { "title": "Mambo" },
  { "title": "Mande Pop" },
  { "title": "Mandopop" },
  { "title": "Manele" },
  { "title": "Marching Band" },
  { "title": "Mariachi" },
  { "title": "Martial Industrial" },
  { "title": "Mashup" },
  { "title": "Math Pop" },
  { "title": "Math Rock" },
  { "title": "Mathcore" },
  { "title": "Mbalax" },
  { "title": "Medieval" },
  { "title": "Medieval Rock" },
  { "title": "Meditation" },
  { "title": "Melancholia" },
  { "title": "Melbourne Bounce" },
  { "title": "Mellow Gold" },
  { "title": "Melodic Death Metal" },
  { "title": "Melodic Hard Rock" },
  { "title": "Melodic Hardcore" },
  { "title": "Melodic Metalcore" },
  { "title": "Melodic Power Metal" },
  { "title": "Melodic Progressive Metal" },
  { "title": "Memphis Blues" },
  { "title": "Memphis Hip Hop" },
  { "title": "Memphis Soul" },
  { "title": "Merengue" },
  { "title": "Merengue Urbano" },
  { "title": "Merseybeat" },
  { "title": "Metal" },
  { "title": "Metal Guitar" },
  { "title": "Metalcore" },
  { "title": "Metropopolis" },
  { "title": "Mexican Indie" },
  { "title": "Mexican Rock-and-roll" },
  { "title": "Mexican Son" },
  { "title": "Mexican Traditional" },
  { "title": "Miami Bass" },
  { "title": "Michigan Indie" },
  { "title": "Microhouse" },
  { "title": "Military Band" },
  { "title": "Minimal" },
  { "title": "Minimal Dub" },
  { "title": "Minimal Dubstep" },
  { "title": "Minimal Melodic Techno" },
  { "title": "Minimal Tech House" },
  { "title": "Minimal Techno" },
  { "title": "Minimal Wave" },
  { "title": "Mizrahi" },
  { "title": "Mod Revival" },
  { "title": "Modern Blues" },
  { "title": "Modern Classical" },
  { "title": "Modern Country Rock" },
  { "title": "Modern Downshift" },
  { "title": "Modern Free Jazz" },
  { "title": "Modern Performance" },
  { "title": "Modern Southern Rock" },
  { "title": "Modern Uplift" },
  { "title": "Monastic" },
  { "title": "Moombahton" },
  { "title": "Morna" },
  { "title": "Motivation" },
  { "title": "Motown" },
  { "title": "Movie Tunes" },
  { "title": "Mpb" },
  { "title": "Musica Para Ninos" },
  { "title": "Musiikkia Lapsille" },
  { "title": "Musique Concrete" },
  { "title": "Musique Pour Enfants" },
  { "title": "Muziek Voor Kinderen" },
  { "title": "Nasheed" },
  { "title": "Nashville Sound" },
  { "title": "Native American" },
  { "title": "Necrogrind" },
  { "title": "Neo Classical Metal" },
  { "title": "Neo Honky Tonk" },
  { "title": "Neo Mellow" },
  { "title": "Neo Metal" },
  { "title": "Neo Soul" },
  { "title": "Neo Soul-jazz" },
  { "title": "Neo-industrial Rock" },
  { "title": "Neo-pagan" },
  { "title": "Neo-progressive" },
  { "title": "Neo-psychedelic" },
  { "title": "Neo-rockabilly" },
  { "title": "Neo-singer-songwriter" },
  { "title": "Neo-synthpop" },
  { "title": "Neo-trad Metal" },
  { "title": "Neo-traditional Country" },
  { "title": "Neoclassical" },
  { "title": "Neofolk" },
  { "title": "Nepali" },
  { "title": "Nerdcore" },
  { "title": "Neue Deutsche Harte" },
  { "title": "Neue Deutsche Welle" },
  { "title": "Neurofunk" },
  { "title": "Neurostep" },
  { "title": "New Age" },
  { "title": "New Age Piano" },
  { "title": "New Americana" },
  { "title": "New Beat" },
  { "title": "New Jack Smooth" },
  { "title": "New Jack Swing" },
  { "title": "New Orleans Blues" },
  { "title": "New Orleans Jazz" },
  { "title": "New Rave" },
  { "title": "New Romantic" },
  { "title": "New Tribe" },
  { "title": "New Wave" },
  { "title": "New Wave Pop" },
  { "title": "New Weird America" },
  { "title": "Ninja" },
  { "title": "Nintendocore" },
  { "title": "Nl Folk" },
  { "title": "No Wave" },
  { "title": "Noise" },
  { "title": "Noise Pop" },
  { "title": "Noise Punk" },
  { "title": "Noise Rock" },
  { "title": "Nordic Folk" },
  { "title": "Nordic House" },
  { "title": "Norteno" },
  { "title": "Northern Irish Indie" },
  { "title": "Northern Soul" },
  { "title": "Norwegian Gospel" },
  { "title": "Norwegian Hip Hop" },
  { "title": "Norwegian Jazz" },
  { "title": "Norwegian Metal" },
  { "title": "Norwegian Pop" },
  { "title": "Norwegian Punk" },
  { "title": "Norwegian Rock" },
  { "title": "Nu Age" },
  { "title": "Nu Disco" },
  { "title": "Nu Electro" },
  { "title": "Nu Gaze" },
  { "title": "Nu Jazz" },
  { "title": "Nu Metal" },
  { "title": "Nu Skool Breaks" },
  { "title": "Nu-cumbia" },
  { "title": "Nueva Cancion" },
  { "title": "Nursery" },
  { "title": "Nwobhm" },
  { "title": "Nwothm" },
  { "title": "Nz Indie" },
  { "title": "Oi" },
  { "title": "Old School Hip Hop" },
  { "title": "Old-time" },
  { "title": "Opera" },
  { "title": "Operatic Pop" },
  { "title": "Opm" },
  { "title": "Oratory" },
  { "title": "Orchestral" },
  { "title": "Organic Ambient" },
  { "title": "Orgcore" },
  { "title": "Orquesta Tipica" },
  { "title": "Orquesta Tropical" },
  { "title": "Oshare Kei" },
  { "title": "Ostrock" },
  { "title": "Outer Hip Hop" },
  { "title": "Outlaw Country" },
  { "title": "Outsider" },
  { "title": "Outsider House" },
  { "title": "P Funk" },
  { "title": "Pagan Black Metal" },
  { "title": "Pagode" },
  { "title": "Pakistani Pop" },
  { "title": "Permanent Wave" },
  { "title": "Persian Pop" },
  { "title": "Persian Traditional" },
  { "title": "Perth Indie" },
  { "title": "Peruvian Rock" },
  { "title": "Piano Blues" },
  { "title": "Piano Rock" },
  { "title": "Piedmont Blues" },
  { "title": "Pipe Band" },
  { "title": "Poetry" },
  { "title": "Polish Hip Hop" },
  { "title": "Polish Indie" },
  { "title": "Polish Jazz" },
  { "title": "Polish Pop" },
  { "title": "Polish Punk" },
  { "title": "Polish Reggae" },
  { "title": "Polka" },
  { "title": "Polynesian Pop" },
  { "title": "Polyphony" },
  { "title": "Pop" },
  { "title": "Pop Christmas" },
  { "title": "Pop Emo" },
  { "title": "Pop House" },
  { "title": "Pop Punk" },
  { "title": "Pop Rap" },
  { "title": "Pop Rock" },
  { "title": "Popgaze" },
  { "title": "Porro" },
  { "title": "Portland Indie" },
  { "title": "Portuguese Pop" },
  { "title": "Portuguese Rock" },
  { "title": "Post Rock" },
  { "title": "Post-disco" },
  { "title": "Post-disco Soul" },
  { "title": "Post-grunge" },
  { "title": "Post-hardcore" },
  { "title": "Post-metal" },
  { "title": "Post-post-hardcore" },
  { "title": "Post-punk" },
  { "title": "Power Blues-rock" },
  { "title": "Power Electronics" },
  { "title": "Power Metal" },
  { "title": "Power Noise" },
  { "title": "Power Pop" },
  { "title": "Power Violence" },
  { "title": "Power-pop Punk" },
  { "title": "Praise" },
  { "title": "Progressive Alternative" },
  { "title": "Progressive Bluegrass" },
  { "title": "Progressive Electro House" },
  { "title": "Progressive House" },
  { "title": "Progressive Metal" },
  { "title": "Progressive Psytrance" },
  { "title": "Progressive Rock" },
  { "title": "Progressive Trance" },
  { "title": "Progressive Trance House" },
  { "title": "Progressive Uplifting Trance" },
  { "title": "Protopunk" },
  { "title": "Psych Gaze" },
  { "title": "Psychedelic Blues-rock" },
  { "title": "Psychedelic Rock" },
  { "title": "Psychedelic Trance" },
  { "title": "Psychill" },
  { "title": "Psychobilly" },
  { "title": "Pub Rock" },
  { "title": "Puerto Rican Rock" },
  { "title": "Punjabi" },
  { "title": "Punk" },
  { "title": "Punk Blues" },
  { "title": "Punk Christmas" },
  { "title": "Punk Ska" },
  { "title": "Qawwali" },
  { "title": "Quebecois" },
  { "title": "Quiet Storm" },
  { "title": "R&b" },
  { "title": "Ragga Jungle" },
  { "title": "Ragtime" },
  { "title": "Rai" },
  { "title": "Ranchera" },
  { "title": "Rap" },
  { "title": "Rap Metal" },
  { "title": "Rap Metalcore" },
  { "title": "Rap Rock" },
  { "title": "Raw Black Metal" },
  { "title": "Re:techno" },
  { "title": "Reading" },
  { "title": "Rebetiko" },
  { "title": "Reggae" },
  { "title": "Reggae Fusion" },
  { "title": "Reggae Rock" },
  { "title": "Reggaeton" },
  { "title": "Regional Mexican" },
  { "title": "Relaxative" },
  { "title": "Remix" },
  { "title": "Renaissance" },
  { "title": "Retro Electro" },
  { "title": "Retro Metal" },
  { "title": "Rhythm And Boogie" },
  { "title": "Riddim" },
  { "title": "Rio De La Plata" },
  { "title": "Riot Grrrl" },
  { "title": "Rock" },
  { "title": "Rock Catala" },
  { "title": "Rock En Espanol" },
  { "title": "Rock Gaucho" },
  { "title": "Rock Noise" },
  { "title": "Rock Steady" },
  { "title": "Rock-and-roll" },
  { "title": "Rockabilly" },
  { "title": "Romanian Pop" },
  { "title": "Romanian Rock" },
  { "title": "Romantic" },
  { "title": "Roots Reggae" },
  { "title": "Roots Rock" },
  { "title": "Rumba" },
  { "title": "Russian Alternative" },
  { "title": "Russian Hip Hop" },
  { "title": "Russian Pop" },
  { "title": "Russian Punk" },
  { "title": "Russian Rock" },
  { "title": "Rva Indie" },
  { "title": "Salsa" },
  { "title": "Salsa International" },
  { "title": "Samba" },
  { "title": "Saxophone" },
  { "title": "Schlager" },
  { "title": "Schranz" },
  { "title": "Scorecore" },
  { "title": "Scottish Rock" },
  { "title": "Scratch" },
  { "title": "Screamo" },
  { "title": "Screamo Punk" },
  { "title": "Screamocore" },
  { "title": "Seattle Indie" },
  { "title": "Sega" },
  { "title": "Serialism" },
  { "title": "Sertanejo" },
  { "title": "Sertanejo Tradicional" },
  { "title": "Sertanejo Universitario" },
  { "title": "Sevdah" },
  { "title": "Shanty" },
  { "title": "Sheffield Indie" },
  { "title": "Shibuya-kei" },
  { "title": "Shimmer Pop" },
  { "title": "Shimmer Psych" },
  { "title": "Shiver Pop" },
  { "title": "Shoegaze" },
  { "title": "Show Tunes" },
  { "title": "Singaporean Pop" },
  { "title": "Singer-songwriter" },
  { "title": "Sinhala" },
  { "title": "Ska" },
  { "title": "Ska Punk" },
  { "title": "Ska Revival" },
  { "title": "Skate Punk" },
  { "title": "Skiffle" },
  { "title": "Skinhead Oi" },
  { "title": "Skinhead Reggae" },
  { "title": "Skweee" },
  { "title": "Slam Death Metal" },
  { "title": "Slash Punk" },
  { "title": "Slc Indie" },
  { "title": "Sleaze Rock" },
  { "title": "Sleep" },
  { "title": "Slovak Hip Hop" },
  { "title": "Slovak Pop" },
  { "title": "Slovenian Rock" },
  { "title": "Slow Core" },
  { "title": "Sludge Metal" },
  { "title": "Smooth Jazz" },
  { "title": "Smooth Urban R&b" },
  { "title": "Soca" },
  { "title": "Soda Pop" },
  { "title": "Soft Rock" },
  { "title": "Solipsynthm" },
  { "title": "Soukous" },
  { "title": "Soul" },
  { "title": "Soul Blues" },
  { "title": "Soul Christmas" },
  { "title": "Soul Flow" },
  { "title": "Soul Jazz" },
  { "title": "Soundtrack" },
  { "title": "South African Jazz" },
  { "title": "Southern Gospel" },
  { "title": "Southern Hip Hop" },
  { "title": "Southern Rock" },
  { "title": "Southern Soul" },
  { "title": "Southern Soul Blues" },
  { "title": "Space Rock" },
  { "title": "Spanish Classical" },
  { "title": "Spanish Folk" },
  { "title": "Spanish Hip Hop" },
  { "title": "Spanish Indie Pop" },
  { "title": "Spanish Indie Rock" },
  { "title": "Spanish Invasion" },
  { "title": "Spanish New Wave" },
  { "title": "Spanish Pop" },
  { "title": "Spanish Pop Rock" },
  { "title": "Spanish Punk" },
  { "title": "Spanish Reggae" },
  { "title": "Speed Garage" },
  { "title": "Speed Metal" },
  { "title": "Speedcore" },
  { "title": "Spoken Word" },
  { "title": "Spytrack" },
  { "title": "Steampunk" },
  { "title": "Steelpan" },
  { "title": "Stl Indie" },
  { "title": "Stomp And Flutter" },
  { "title": "Stomp And Holler" },
  { "title": "Stomp And Whittle" },
  { "title": "Stomp Pop" },
  { "title": "Stoner Metal" },
  { "title": "Stoner Rock" },
  { "title": "Straight Edge" },
  { "title": "Street Punk" },
  { "title": "Stride" },
  { "title": "String Band" },
  { "title": "String Folk" },
  { "title": "String Quartet" },
  { "title": "Substep" },
  { "title": "Sunset Lounge" },
  { "title": "Suomi Rock" },
  { "title": "Surf Music" },
  { "title": "Swamp Blues" },
  { "title": "Swamp Pop" },
  { "title": "Swedish Alternative Rock" },
  { "title": "Swedish Hard Rock" },
  { "title": "Swedish Hip Hop" },
  { "title": "Swedish Indie Pop" },
  { "title": "Swedish Indie Rock" },
  { "title": "Swedish Jazz" },
  { "title": "Swedish Metal" },
  { "title": "Swedish Pop" },
  { "title": "Swedish Pop Punk" },
  { "title": "Swedish Prog" },
  { "title": "Swedish Punk" },
  { "title": "Swedish Reggae" },
  { "title": "Swedish Soft Pop" },
  { "title": "Swedish Synthpop" },
  { "title": "Swing" },
  { "title": "Swirl Psych" },
  { "title": "Swiss Folk" },
  { "title": "Swiss Hip Hop" },
  { "title": "Swiss Rock" },
  { "title": "Symphonic Black Metal" },
  { "title": "Symphonic Metal" },
  { "title": "Symphonic Rock" },
  { "title": "Synthpop" },
  { "title": "Taiwanese Pop" },
  { "title": "Talent Show" },
  { "title": "Tango" },
  { "title": "Tech House" },
  { "title": "Technical Brutal Death Metal" },
  { "title": "Technical Death Metal" },
  { "title": "Techno" },
  { "title": "Teen Pop" },
  { "title": "Tejano" },
  { "title": "Tekno" },
  { "title": "Terrorcore" },
  { "title": "Texas Blues" },
  { "title": "Texas Country" },
  { "title": "Thai Indie" },
  { "title": "Thai Pop" },
  { "title": "Thrash Core" },
  { "title": "Thrash Metal" },
  { "title": "Thrash-groove Metal" },
  { "title": "Throat Singing" },
  { "title": "Tibetan" },
  { "title": "Tico" },
  { "title": "Timba" },
  { "title": "Tin Pan Alley" },
  { "title": "Traditional Blues" },
  { "title": "Traditional British Folk" },
  { "title": "Traditional Country" },
  { "title": "Traditional Folk" },
  { "title": "Traditional Funk" },
  { "title": "Traditional Irish Folk" },
  { "title": "Traditional Reggae" },
  { "title": "Traditional Rock 'N Roll" },
  { "title": "Traditional Rockabilly" },
  { "title": "Traditional Scottish Folk" },
  { "title": "Traditional Ska" },
  { "title": "Traditional Soul" },
  { "title": "Traditional Swing" },
  { "title": "Trance" },
  { "title": "Trance Hop" },
  { "title": "Trap Music" },
  { "title": "Trapstep" },
  { "title": "Trash Rock" },
  { "title": "Triangle Indie" },
  { "title": "Tribal House" },
  { "title": "Tribute" },
  { "title": "Trip Hop" },
  { "title": "Tropical" },
  { "title": "Trova" },
  { "title": "Turbo Folk" },
  { "title": "Turkish Alternative" },
  { "title": "Turkish Classical" },
  { "title": "Turkish Folk" },
  { "title": "Turkish Hip Hop" },
  { "title": "Turkish Jazz" },
  { "title": "Turkish Pop" },
  { "title": "Turkish Rock" },
  { "title": "Turntablism" },
  { "title": "Twee Indie Pop" },
  { "title": "Twee Pop" },
  { "title": "Twin Cities Indie" },
  { "title": "Tzadik" },
  { "title": "Uk Dub" },
  { "title": "Uk Garage" },
  { "title": "Uk Hip Hop" },
  { "title": "Uk Post-punk" },
  { "title": "Ukrainian Rock" },
  { "title": "Ukulele" },
  { "title": "Unblack Metal" },
  { "title": "Underground Hip Hop" },
  { "title": "Underground Latin Hip Hop" },
  { "title": "Underground Pop Rap" },
  { "title": "Underground Power Pop" },
  { "title": "Underground Rap" },
  { "title": "Uplifting Trance" },
  { "title": "Urban Contemporary" },
  { "title": "Vallenato" },
  { "title": "Vancouver Indie" },
  { "title": "Vapor House" },
  { "title": "Vaporwave" },
  { "title": "Vegan Straight Edge" },
  { "title": "Vegas Indie" },
  { "title": "Velha Guarda" },
  { "title": "Venezuelan Rock" },
  { "title": "Video Game Music" },
  { "title": "Vienna Indie" },
  { "title": "Vietnamese Pop" },
  { "title": "Viking Metal" },
  { "title": "Vintage Chanson" },
  { "title": "Vintage Country Folk" },
  { "title": "Vintage Gospel" },
  { "title": "Vintage Jazz" },
  { "title": "Vintage Reggae" },
  { "title": "Vintage Rockabilly" },
  { "title": "Vintage Schlager" },
  { "title": "Vintage Swedish Pop" },
  { "title": "Vintage Swing" },
  { "title": "Vintage Swoon" },
  { "title": "Vintage Tango" },
  { "title": "Vintage Western" },
  { "title": "Violin" },
  { "title": "Viral Pop" },
  { "title": "Visual Kei" },
  { "title": "Vocal House" },
  { "title": "Vocal Jazz" },
  { "title": "Vocaloid" },
  { "title": "Volksmusik" },
  { "title": "Warm Drone" },
  { "title": "Welsh Rock" },
  { "title": "West African Jazz" },
  { "title": "West Coast Rap" },
  { "title": "Western Swing" },
  { "title": "Wind Ensemble" },
  { "title": "Witch House" },
  { "title": "Wonky" },
  { "title": "Workout" },
  { "title": "World" },
  { "title": "World Chill" },
  { "title": "World Christmas" },
  { "title": "World Fusion" },
  { "title": "Worship" },
  { "title": "Wrestling" },
  { "title": "Wrock" },
  { "title": "Ye Ye" },
  { "title": "Yoik" },
  { "title": "Yugoslav Rock" },
  { "title": "Zeuhl" },
  { "title": "Zillertal" },
  { "title": "Zim" },
  { "title": "Zolo" },
  { "title": "Zouglou" },
  { "title": "Zouk" },
  { "title": "Zydeco" }
]
